mesos.interface-1.11.0-py2.7-nspkg.pth
mesos.interface-1.11.0.dist-info/namespace_packages.txt
mesos.interface-1.11.0.dist-info/top_level.txt
mesos.interface-1.11.0.dist-info/METADATA
mesos.interface-1.11.0.dist-info/WHEEL
mesos.interface-1.11.0.dist-info/RECORD
mesos.interface-1.11.0.dist-info/metadata.json
mesos.interface-1.11.0.dist-info/DESCRIPTION.rst
mesos/interface/mesos_pb2.py
mesos/interface/__init__.py
