Metadata-Version: 2.0
Name: mesos.interface
Version: 1.11.0
Summary: Mesos interfaces
Home-page: http://pypi.python.org/pypi/mesos.interface
Author: Apache Mesos
Author-email: dev@mesos.apache.org
License: Apache 2.0
Keywords: mesos
Platform: UNKNOWN
Requires-Dist: google-common (>=0.0.1)
Requires-Dist: protobuf (>=3.5.0,<4)
